{
  "main": {
    "id": "eb06152a0b74bb38",
    "type": "split",
    "children": [
      {
        "id": "79236679aaf8029f",
        "type": "tabs",
        "children": [
          {
            "id": "71aecf5fa0f10c18",
            "type": "leaf",
            "state": {
              "type": "markdown",
              "state": {
                "file": "2. Smester II/1. EMA/EKONOMI MANAJERIAL.md",
                "mode": "source",
                "source": false
              }
            }
          }
        ]
      }
    ],
    "direction": "vertical"
  },
  "left": {
    "id": "b2ccfa181a36b241",
    "type": "split",
    "children": [
      {
        "id": "a2c54fad080f487d",
        "type": "tabs",
        "children": [
          {
            "id": "dc801a98408203eb",
            "type": "leaf",
            "state": {
              "type": "file-explorer",
              "state": {
                "sortOrder": "alphabetical"
              }
            }
          },
          {
            "id": "8f4dd183aaecb5bd",
            "type": "leaf",
            "state": {
              "type": "search",
              "state": {
                "query": "",
                "matchingCase": false,
                "explainSearch": false,
                "collapseAll": false,
                "extraContext": false,
                "sortOrder": "alphabetical"
              }
            }
          },
          {
            "id": "bac4ad0e649134bf",
            "type": "leaf",
            "state": {
              "type": "starred",
              "state": {}
            }
          }
        ]
      }
    ],
    "direction": "horizontal",
    "width": 200
  },
  "right": {
    "id": "adc0635e157e6dbd",
    "type": "split",
    "children": [
      {
        "id": "e8402b51f61db8a3",
        "type": "tabs",
        "children": [
          {
            "id": "e85739e942ed0517",
            "type": "leaf",
            "state": {
              "type": "backlink",
              "state": {
                "file": "2. Smester II/1. EMA/EKONOMI MANAJERIAL.md",
                "collapseAll": false,
                "extraContext": false,
                "sortOrder": "alphabetical",
                "showSearch": false,
                "searchQuery": "",
                "backlinkCollapsed": false,
                "unlinkedCollapsed": false
              }
            }
          },
          {
            "id": "0d1d568f771ea4ac",
            "type": "leaf",
            "state": {
              "type": "outgoing-link",
              "state": {
                "file": "2. Smester II/1. EMA/EKONOMI MANAJERIAL.md",
                "linksCollapsed": false,
                "unlinkedCollapsed": true
              }
            }
          },
          {
            "id": "f7e7cd8d79cd58d6",
            "type": "leaf",
            "state": {
              "type": "tag",
              "state": {
                "sortOrder": "frequency",
                "useHierarchy": true
              }
            }
          },
          {
            "id": "95349a09d622de17",
            "type": "leaf",
            "state": {
              "type": "outline",
              "state": {
                "file": "2. Smester II/1. EMA/EKONOMI MANAJERIAL.md"
              }
            }
          },
          {
            "id": "a3e42cc4677a9382",
            "type": "leaf",
            "state": {
              "type": "calendar",
              "state": {}
            }
          },
          {
            "id": "65107331d19c9853",
            "type": "leaf",
            "state": {
              "type": "FANTASY_CALENDAR",
              "state": {}
            }
          }
        ],
        "currentTab": 5
      }
    ],
    "direction": "horizontal",
    "width": 272.5
  },
  "active": "71aecf5fa0f10c18",
  "lastOpenFiles": [
    "2. Smester II/1. EMA/2022-08-15 EMA.md",
    "2. Smester II/1. EMA/EKONOMI MANAJERIAL.md",
    "SETUP/templates/terminologi.md",
    "terminologi/111101010101.md",
    "terminologi/121212312.md",
    "terminlogi/111111.md",
    "terminologi/31989189487193849189.md",
    "terminologi/12121213221.md",
    "terminologi/121212312312.md",
    "terminologi/daskjkljalkdjlkas.md"
  ]
}